.gitkeep
singleImagesToPDF/.gitkeep
singleImagesToPDF/__init__.py
singleImagesToPDF/pdfFromMultiImages.py
singleImagesToPDF/pdfImgCrypt.py
singleImagesToPDF/salt
singleImagesToPDF/string1
singleImagesToPDF/token1
singleImagesToPDF-4.2.1.dist-info/.gitkeep
singleImagesToPDF-4.2.1.dist-info/LICENSE.txt
singleImagesToPDF-4.2.1.dist-info/METADATA
singleImagesToPDF-4.2.1.dist-info/WHEEL
singleImagesToPDF-4.2.1.dist-info/top_level.txt
singleImagesToPDF-4.2.1.dist-info/RECORD
