Metadata-Version: 2.1
Name: singleImagesToPDF
Version: 4.2.1
Summary: It helps you convert all the images in the current working directory (os.getcwd()) to a single pdf file
Home-page: https://gitlab.com/antoreep_jana/singleimagestopdf/tree/master
Download-URL: https://gitlab.com/antoreep_jana/singleimagestopdf/-/archive/v4.2.1/singleimagestopdf-v4.2.1.tar.gz
Author: Antoreep Jana
Author-email: antoreepjana@gmail.com
License: MIT
Keywords: Image to PDF,Merge Images,pdf,PDF,PDF maker from images,jpeg to pdf,Convert Images to PDF
Classifier: Development Status :: 5 - Production/Stable
Classifier: Intended Audience :: Developers
Classifier: Topic :: Software Development :: Build Tools
Classifier: License :: OSI Approved :: MIT License
Classifier: Programming Language :: Python :: 3
Classifier: Programming Language :: Python :: 3.4
Classifier: Programming Language :: Python :: 3.5
Classifier: Programming Language :: Python :: 3.6
License-File: LICENSE.txt
